devtools_markdown_table/__init__.py
devtools_markdown_table-1.0.1.dist-info/METADATA
devtools_markdown_table-1.0.1.dist-info/WHEEL
devtools_markdown_table-1.0.1.dist-info/top_level.txt
devtools_markdown_table-1.0.1.dist-info/RECORD
